claude_hooks/__init__.py
claude_hooks/cli.py
claude_hooks/main.py
claude_hooks_template-1.6.4.dist-info/METADATA
claude_hooks_template-1.6.4.dist-info/WHEEL
claude_hooks_template-1.6.4.dist-info/entry_points.txt
claude_hooks_template-1.6.4.dist-info/licenses/LICENSE
claude_hooks_template-1.6.4.dist-info/RECORD
