Metadata-Version: 2.4
Name: claude-hooks-template
Version: 1.6.4
Summary: CLI tool for configuring Claude Code hooks in projects
Project-URL: Homepage, https://github.com/stevennevins/claude-hooks
Project-URL: Repository, https://github.com/stevennevins/claude-hooks
Project-URL: Issues, https://github.com/stevennevins/claude-hooks/issues
Project-URL: Documentation, https://github.com/stevennevins/claude-hooks#readme
Author-email: Steven Nevins <snevins@gmail.com>
License: MIT
License-File: LICENSE
Keywords: automation,claude-code,cli,hooks
Classifier: Development Status :: 4 - Beta
Classifier: Intended Audience :: Developers
Classifier: License :: OSI Approved :: MIT License
Classifier: Programming Language :: Python :: 3
Classifier: Programming Language :: Python :: 3.10
Classifier: Programming Language :: Python :: 3.11
Classifier: Programming Language :: Python :: 3.12
Classifier: Topic :: Software Development :: Libraries :: Application Frameworks
Requires-Python: >=3.10
